Workbook

Sheet Ringkasan
A1: SISKOP — Daftar Rumus Sistem
A2: Disusun dari kode sumber feature/reports-alignment-v2@99a527a, 11 Oktober 2026. Edisi awal: main@0154f9c, 29 September 2026.
A4: Isi workbook
A5: Daftar Rumus | B5: 67 rumus bisnis: definisi, variabel, aturan, jenis aritmetika, file sumber, dasar regulasi.
A6: Simulasi | B6: Kalkulator hidup untuk rumus utama (bagian A–P). Ubah sel kuning berteks biru.
A7: Parameter | B7: Semua konstanta & batas regulasi yang dipakai kode, termasuk batas kelas KSP dan akun tujuan penutupan.
A8: Jurnal Otomatis | B8: 21 pola jurnal Debit/Kredit per jenis transaksi.
A9: Temuan | B9: 11 catatan dari review rumus (float, pembulatan, penamaan, data basi).
A11: Legenda warna
A12: Teks biru + isi kuning | B12: Input — boleh diubah
A13: Teks hitam | B13: Hasil rumus — jangan ditimpa
A14: Teks hijau | B14: Rujukan ke sheet Parameter
A15: Isi kuning muda (Aritmetika) | B15: Rumus dihitung dengan number (float), bukan Decimal
A17: Catatan | B17: Hasil Simulasi mengikuti rumus kode, tetapi Excel menghitung dengan float. Untuk angka resmi, gunakan hasil aplikasi.

Sheet Daftar Rumus
A1: Daftar Rumus SISKOP
A2: Setiap rumus bisnis di kode, per feature/reports-alignment-v2@99a527a (2026-10-11). Kolom 'Aritmetika' menandai apakah dihitung dengan Decimal atau number (float).
A4: No | B4: Modul | C4: Nama Rumus | D4: Rumus | E4: Variabel / Keterangan | F4: Aturan, Batas & Pembulatan | G4: Aritmetika | H4: Sumber Kode | I4: Dasar Regulasi / Keputusan | J4: Simulasi
A5: SIM-01 | B5: Simpanan | C5: Bunga simpanan per periode | D5: Bunga = ROUND(Saldo × Rate ÷ D, 2) D = 360 (DAILY), 12 (MONTHLY), 1 (YEARLY) | E5: Rate = % per tahun dari produk simpanan (SavingConfig.rate); periodUnit hanya menentukan frekuensi kredit | F5: Rate ≤ 9%/tahun. Dibulatkan 2 desimal | G5: number (float) | H5: lib/saving-calc.ts calculateSavingInterest | I5: Permenkop UKM 8/2023 Pasal 26 | J5: D
A6: SIM-02 | B6: Simpanan | C6: Akrual bunga harian (scheduler) | D6: Bunga = ROUND(Saldo × Rate ÷ 36.000, 2) × HariTerlewat HariTerlewat = hari ini − lastInterestAt (run pertama = 1) | E6: Dijalankan harian; saldo dikunci (FOR UPDATE) | F6: Dibulatkan per hari lalu dikali hari; tidak pernah menagih mundur sampai pembukaan rekening | G6: Decimal | H6: savings/daily-interest.ts | J6: D
A7: SIM-03 | B7: Simpanan | C7: Rekening Koran — Saldo Akhir | D7: SaldoAkhir = Saving.balance − Σ mutasi bertanda setelah akhir periode | E7: Mutasi bertanda: PENARIKAN = −jumlah; SETORAN/BUNGA = +jumlah | F7: Periode maks. 366 hari; default awal bulan s/d hari ini | G7: Decimal | H7: savings/service.ts getSavingStatement | J7: E
A8: SIM-04 | B8: Simpanan | C8: Rekening Koran — Saldo Awal & berjalan | D8: SaldoAwal = SaldoAkhir − Σ mutasi bertanda dalam periode Saldo_i = Saldo_(i−1) + Kredit_i − Debit_i | E8: Kredit = setoran + bunga; Debit = penarikan (dari sisi pemilik rekening) | G8: Decimal | H8: savings/service.ts getSavingStatement | J8: E
A9: SIM-05 | B9: Simpanan | C9: Syarat tarik Simpanan Pokok | D9: Boleh tarik Pokok ⇔ tidak ada pinjaman ACTIVE; Saldo ≥ jumlah tarik | F9: Belum ada batas minimum/nol (QA D2) | G9: Decimal | H9: savings/service.ts withdrawFromSaving | I9: AD/ART; UU 25/1992
A10: PIN-01 | B10: Pinjaman | C10: Angsuran anuitas (KONVENSIONAL + BUNGA) | D10: r = Rate ÷ 12 Angsuran = P × r ÷ (1 − (1 + r)^−n) Total = Angsuran × n; Bunga = Total − P Jika r = 0: Angsuran = P ÷ n | E10: P = pokok; n = tenor bulan | F10: Hanya frekuensi MONTHLY. Dibulatkan 2 desimal | G10: number (float) | H10: lib/loan-calc.ts calculateLoan | I10: Rate ≤ 24%/tahun (Pasal 27) | J10: A
A11: PIN-02 | B11: Pinjaman | C11: Flat margin (SYARIAH atau MARGIN) | D11: Margin = P × Rate × n ÷ 12 Total = P + Margin; Angsuran = Total ÷ n | E11: Murabahah / flat | F11: Berlaku untuk semua frekuensi; n untuk DAILY/WEEKLY = PIN-04 | G11: number (float) | H11: lib/loan-calc.ts calculateLoan | J11: B
A12: PIN-03 | B12: Pinjaman | C12: Bunga harian flat (HARIAN) | D12: Bunga = P × Rate ÷ 360 × HariTenor Total = P + Bunga | E12: HariTenor: MONTHLY = hari kalender riil pencairan → jatuh tempo; DAILY = jumlah cicilan; WEEKLY = cicilan × 7; tanpa tanggal = n × 30 | G12: number (float) | H12: lib/loan-calc.ts; loans/service.ts createLoan | J12: C
A13: PIN-04 | B13: Pinjaman | C13: Tenor bulan untuk DAILY/WEEKLY | D13: TenorBulan = MAX(1, ROUNDUP(Hari ÷ 30)) Hari = cicilan (DAILY) atau cicilan × 7 (WEEKLY) | E13: Dipakai untuk angsuran bulanan & flat margin | F13: Pembulatan ke atas menaikkan margin flat (lihat Temuan T4) | G13: integer | H13: loans/service.ts createLoan | J13: C
A14: PIN-05 | B14: Pinjaman | C14: Nominal cicilan jadwal | D14: Rata = Total ÷ JumlahCicilan DAILY/WEEKLY: Cicilan = ROUNDUP(Rata ÷ 500) × 500 MONTHLY: Cicilan = ROUND(Rata, 2) Cicilan terakhir = Total − Σ cicilan sebelumnya | F14: Σ cicilan = Total persis | G14: Decimal | H14: lib/installment-schedule.ts buildSchedule | I14: Keputusan pasar D8 (Rp500) | J14: C
A15: PIN-06 | B15: Pinjaman | C15: Porsi pokok & bunga per cicilan | D15: Pokok_i = ROUND(Cicilan_i × P ÷ Total, 2) Bunga_i = Cicilan_i − Pokok_i Pokok terakhir = P − Σ pokok sebelumnya | G15: Decimal | H15: lib/installment-schedule.ts buildSchedule | J15: C
A16: PIN-07 | B16: Pinjaman | C16: Tanggal jatuh tempo | D16: DAILY: hari operasional ke-i setelah pencairan WEEKLY: pencairan + 7i hari → hari operasional berikutnya MONTHLY: pencairan + i bulan → hari operasional berikutnya | E16: Hari operasional = bukan hari tutup (default Minggu) & bukan hari libur tenant | F16: Tanggal bisnis Asia/Jakarta (UTC+7) | G16: tanggal | H16: lib/installment-schedule.ts; lib/operating-calendar.ts | I16: Keputusan pasar D1
A17: PIN-08 | B17: Pinjaman | C17: Alokasi pembayaran | D17: Untuk tiap cicilan belum lunas, tertua dulu: Dipakai = MIN(sisa bayar, sisa cicilan) Bunga dulu = MIN(Dipakai, sisa bunga); Pokok = Dipakai − Bunga LUNAS jika terbayar ≥ cicilan, else PARTIAL | G17: Decimal | H17: lib/loan-allocation.ts allocatePayment
A18: PIN-09 | B18: Pinjaman | C18: Pemisahan pembayaran (pinjaman tanpa jadwal) | D18: Bunga = ROUND(Bayar × (Total − P) ÷ Total, 2) Pokok = Bayar − Bunga | E18: Hanya pinjaman lama yang belum di-backfill | G18: Decimal | H18: lib/journal.ts splitLoanPayment
A19: PIN-10 | B19: Pinjaman | C19: Sisa pinjaman | D19: Sisa = MAX(0, Sisa − Bayar); status COMPLETED bila 0 | E19: Bayar > Sisa ditolak | F19: Denda diinput manual (tidak dihitung otomatis) | G19: Decimal | H19: loans/service.ts recordLoanPayment | I19: Keputusan pasar D7
A20: PIN-11 | B20: Pinjaman | C20: Override bunga per pinjaman | D20: RateEfektif = rate input bila ≠ rate produk, else rate produk | E20: Wajib isi rateNote bila diubah | F20: ≤ 24%/tahun; tercatat di jejak audit | G20: number (float) | H20: loans/service.ts createLoan | I20: Keputusan pasar D3 | J20: A
A21: PIN-12 | B21: Pinjaman | C21: Hari tunggakan | D21: Dengan jadwal: hari ini − jatuh tempo cicilan belum lunas tertua (0 bila belum jatuh tempo) Tanpa jadwal: maks. hari lewat untuk bulan tanpa pembayaran | F21: Dihitung ulang harian oleh scheduler | G21: integer | H21: lib/kol.ts recalculateKOL | I21: Keputusan pasar D2 | J21: H
A22: PIN-13 | B22: Pinjaman | C22: Kolektibilitas (KOL) | D22: ≤30 Lancar; ≤90 Dalam Perhatian; ≤120 Kurang Lancar; ≤180 Diragukan; >180 Macet | E22: Input = hari tunggakan (PIN-12) | G22: integer | H22: lib/kol.ts getKOLCategory | J22: H
A23: PIN-14 | B23: Pinjaman | C23: BMPP — batas & ruang | D23: Batas = ModalSendiri × % (10% terkait, 15% lainnya) Ruang = MAX(0, Batas − pokok pinjaman ACTIVE) | E23: KSU (>1 unit aktif): Modal Sendiri & pinjaman unit pemberi; tunggal: konsolidasi | G23: Decimal | H23: loans/service.ts computeBmpp | I23: Permenkop UKM 8/2023 Pasal 44–45 | J23: F
A24: PIN-15 | B24: Pinjaman | C24: BMPP — keputusan | D24: Terkait: (aktif + baru) > Batas → DITOLAK Lainnya: ModalSendiri > 0 dan (aktif + baru) > Batas → PERINGATAN, lanjut dengan acknowledgeBmpp | E24: Terkait = pengurus atau pengawas | F24: Modal Sendiri 0 → pihak terkait tidak bisa meminjam | G24: Decimal | H24: loans/service.ts createLoan; lib/regulatory-config.ts | I24: Pasal 44 (blokir), Pasal 45 (peringatan) | J24: F
A25: PIN-16 | B25: Pinjaman | C25: Syarat simpanan pokok | D25: Pinjaman baru hanya bila anggota punya Simpanan Pokok aktif | F25: Pokok bersaldo 0 tetap lolos (Temuan O1 PRD) | G25: boolean | H25: loans/service.ts; savings/service.ts hasPokokSaving
A26: TOK-01 | B26: Toko / POS | C26: Total penjualan & HPP | D26: Total = Σ harga × qty HPP = Σ harga pokok × qty Margin = Total − HPP | E26: Harga dari master produk (bukan dari klien) | F26: Stok harus ≥ qty | G26: Decimal | H26: konsumen/sale.service.ts
A27: TOK-02 | B27: Toko / POS | C27: Nilai restock | D27: Nilai = harga pokok × qty (Dr Persediaan / Cr Kas) | E27: Penyesuaian stok tidak dijurnal | G27: Decimal | H27: konsumen/product.service.ts; lib/journal.ts postStockPurchase
A28: TOK-03 | B28: Toko / POS | C28: Limit Kredit Anggota | D28: Limit = Σ saldo simpanan aktif × 50% Piutang = Σ belanja MEMBER_CREDIT − Σ pelunasan Tersedia = Limit − Piutang Berhak ⇔ punya simpanan aktif dan Limit > 0 | E28: Semua jenis simpanan (Pokok + Wajib + Sukarela) | F28: Dihitung ulang setiap dibaca, tidak disimpan | G28: Decimal | H28: konsumen/credit.service.ts | I28: Keputusan produk | J28: G
A29: PAS-01 | B29: Pasar | C29: Tagihan sewa | D29: Satu tagihan SEWA per ulang tahun periode kontrak (MONTHLY/YEARLY) sejak tanggal mulai Jumlah = rentAmount; jatuh tempo = hari operasional berikutnya | E29: Idempoten per (kontrak, awal periode) | F29: Hanya dibuat pada hari operasional | G29: Decimal | H29: market/charge-generator.ts | I29: Keputusan pasar D1
A30: PAS-02 | B30: Pasar | C30: Tagihan retribusi harian | D30: Satu tagihan RETRIBUSI per hari operasional per tarif DAILY aktif yang cocok (pasar + jenis lapak) Jumlah = levyRate.amount | F30: Retribusi = pendapatan koperasi | G30: Decimal | H30: market/charge-generator.ts | I30: Keputusan pasar D5
A31: PAS-03 | B31: Pasar | C31: Tunggakan angsuran | D31: Σ (pokok + bunga jatuh tempo − pokok + bunga terbayar) cicilan belum lunas dengan jatuh tempo < hari ini | E31: Pinjaman ACTIVE | G31: Decimal | H31: dashboard/service.ts getPasarDashboard
A32: PAS-04 | B32: Pasar | C32: Tunggakan sewa/retribusi | D32: Σ (jumlah − terbayar) tagihan belum lunas dengan jatuh tempo < hari ini | G32: Decimal | H32: dashboard/service.ts getPasarDashboard
A33: PAS-05 | B33: Pasar | C33: Setoran hari ini | D33: Σ expectedTotal batch kolektor dengan tanggal bisnis hari ini | E33: expectedTotal bertambah setiap setoran kolektor | G33: Decimal | H33: collections/service.ts; dashboard/service.ts | J33: M
A34: PAS-06 | B34: Pasar | C34: Selisih setoran kolektor | D34: Selisih = Diterima − Diharapkan Kurang → Dr Piutang Kolektor; Lebih → Cr Selisih Kas | E34: Kolektor tidak boleh memverifikasi batch sendiri | F34: Batch harus SUBMITTED | G34: Decimal | H34: collections/service.ts verifyBatch; lib/journal.ts | J34: M
A35: MOD-01 | B35: Permodalan | C35: Modal Sendiri | D35: MS = Σ saldo akun EKUITAS kelas {Simpanan Pokok, Simpanan Wajib, Modal Tetap, Cadangan Umum, Cadangan Risiko, Hibah} per tanggal + penyesuaian terbaru per cakupan Saldo akun = Kredit − Debit (normal kredit) | E35: Tanpa unit = konsolidasi; dengan unit = unit itu saja | F35: Tidak termasuk Modal Penyertaan, SHU belum dibagi, ekuitas lain | G35: Decimal | H35: reports/capital-service.ts getModalSendiri | I35: Permenkop UKM 8/2023 Pasal 1 angka 23–24 | J35: J
A36: MOD-02 | B36: Permodalan | C36: Rasio Modal Sendiri / Aset | D36: Rasio = MS ÷ Total Aset × 100% | F36: Kosong bila aset 0 | G36: Decimal | H36: dashboard/service.ts getCapitalDashboard | J36: J
A37: MOD-03 | B37: Permodalan | C37: Ambang wajib audit | D37: WAJIB: MS per 31 Des tahun lalu ≥ Rp5 miliar MENDEKATI: MS berjalan ≥ Rp5 miliar Progres = MS ÷ Rp5 miliar | E37: Hanya tenant dengan unit KSP aktif | F37: Notifikasi maks. 1× per jenis per tahun; pengingat, tidak memblokir | G37: Decimal | H37: config/audit-threshold.ts; dashboard/service.ts | I37: Permenkop UKM 2/2024 Pasal 12 | J37: J
A38: MOD-04 | B38: Permodalan | C38: Konsentrasi simpanan | D38: Tampilkan anggota dengan saldo Pokok + Wajib > MS × 20% % = saldo ÷ MS × 100 | F38: Indikator, bukan aturan | G38: Decimal | H38: dashboard/service.ts getCapitalDashboard | J38: J
A39: MOD-05 | B39: Permodalan | C39: Klasifikasi KSP | D39: KSP I/II/III = kelas terendah yang batas anggota, MS dan aset-nya semua terpenuhi; selain itu KSP IV | E39: Batas: lihat sheet Parameter | G39: Decimal | H39: lib/regulatory-config.ts classifyKsp | I39: Permenkop UKM 8/2023 Pasal 49 | J39: K
A40: MOD-06 | B40: Permodalan | C40: Penggunaan BMPP (dashboard) | D40: Penggunaan = pokok aktif ÷ batas BMPP × 100% | E40: Diurutkan dari yang paling dekat batas | G40: Decimal | H40: dashboard/service.ts getCapitalDashboard | J40: F
A41: KUA-01 | B41: Dashboard | C41: Total outstanding | D41: Σ remainingAmount pinjaman ACTIVE (per KOL) | G41: Decimal | H41: dashboard/service.ts getLoanQualityDashboard | J41: I
A42: KUA-02 | B42: Dashboard | C42: Rasio NPL | D42: NPL = (Kurang Lancar + Diragukan + Macet) ÷ Total outstanding × 100% | G42: Decimal | H42: dashboard/service.ts | J42: I
A43: KUA-03 | B43: Dashboard | C43: LDR | D43: LDR = Total outstanding ÷ Σ saldo simpanan non-ekuitas × 100% | E43: Non-ekuitas = selain Pokok & Wajib (yaitu Sukarela) | G43: Decimal | H43: dashboard/service.ts | J43: I
A44: KUA-04 | B44: Dashboard | C44: Pertumbuhan bulanan (12 bulan) | D44: Anggota baru = jumlah anggota dibuat di bulan itu Arus simpanan bersih = Σ setoran + bunga − penarikan Pencairan = Σ pokok dicairkan; Angsuran = Σ pembayaran | G44: Decimal | H44: dashboard/service.ts getGrowthDashboard
A45: KUA-05 | B45: Laporan | C45: Portfolio at Risk (PAR) per bucket | D45: Bucket menurut Loan.daysOverdue: ≤0 CURRENT; ≤30 D1_30; ≤60 D31_60; ≤90 D61_90; >90 D90_PLUS PAR>1 = Σ outstanding (D1_30…D90_PLUS) ÷ Total × 100% PAR>30 = Σ (D31_60…D90_PLUS) ÷ Total × 100% PAR>90 = Σ D90_PLUS ÷ Total × 100% | E45: Hanya pinjaman ACTIVE. Outstanding = pokok belum dibayar (KUA-07). Rasio NPL laporan = PAR>90; sama dengan KL + D + M di KUA-02 karena batas KOL Dalam Perhatian ≤90 hari. | F45: Persen, 2 desimal. Buku kosong → 0 (bukan pembagian nol). Hari tunggakan memakai Loan.daysOverdue hasil job KOL harian (lib/kol.ts), bukan dihitung ulang (lihat Temuan T9). | G45: Decimal | H45: reports/portfolio-service.ts getPortfolioPar; listParLoans | I45: Praktik umum mikrokeuangan (PAR30/PAR90) | J45: N
A46: KUA-06 | B46: Laporan | C46: PAR per produk pinjaman | D46: PAR30_p = Σ outstanding (daysOverdue > 30) ÷ Outstanding produk p × 100% PAR90_p = Σ outstanding (daysOverdue > 90) ÷ Outstanding produk p × 100% | E46: Dikelompokkan per LoanConfig, urut outstanding terbesar. | F46: Persen, 2 desimal; produk tanpa outstanding → 0. | G46: Decimal | H46: reports/portfolio-service.ts getPortfolioPar (byProduct) | J46: N
A47: KUA-07 | B47: Laporan | C47: Outstanding pokok pinjaman | D47: Bila ada jadwal: Σ (principalDue − principalPaid) Bila tanpa jadwal: remainingAmount × principalAmount ÷ totalAmount Bila totalAmount = 0: 0 | E47: Pinjaman lama sebelum fitur jadwal memakai porsi pokok flat (sama dengan PIN-09). Lihat Temuan T11. | F47: Tidak dibulatkan di SQL; dibulatkan 2 desimal saat ditampilkan. | G47: Decimal | H47: reports/portfolio-service.ts outstandingSql | J47: N
A48: KUA-08 | B48: Laporan | C48: Efisiensi penagihan | D48: Efisiensi = Σ (principalPaid + interestPaid) cicilan jatuh tempo dalam periode ÷ Σ (principalDue + interestDue) cicilan itu × 100% | E48: Cicilan pinjaman ACTIVE atau COMPLETED dengan jatuh tempo dalam [dari, sampai]. Kas diterima periode = Σ LoanPayment.amount (paidAt dalam periode), hanya informasi. Pinjaman ACTIVE tanpa jadwal tidak terukur dan hanya dihitung jumlahnya. | F48: Kosong (null) bila tidak ada tagihan jatuh tempo. 'Terbayar' kumulatif sampai sekarang, bukan sampai akhir periode, sehingga periode lama bisa naik seiring waktu (lihat Temuan T10). | G48: Decimal | H48: reports/portfolio-service.ts getCollectionEfficiency | J48: N
A49: LAP-01 | B49: Laporan | C49: SHU berjalan | D49: SHU = Σ kontribusi PENDAPATAN − Σ kontribusi BEBAN dalam periode Kontribusi akun = saldo sisi normal; akun kontra bernilai negatif | E49: Akun induk (header) hanya ditampilkan, tidak dijumlahkan (menghindari hitung ganda). | F49: Entri penutup (entryType PENUTUP, Tutup Buku) dikecualikan dari mutasi periode agar laba rugi tahun yang sudah ditutup tetap menampilkan aktivitas aslinya. Pembulatan 2 desimal. | G49: Decimal | H49: reports/regulatory-service.ts getLaporanHasilUsaha | J49: L
A50: LAP-02 | B50: Laporan | C50: Identitas Neraca | D50: Aset = Kewajiban + Ekuitas + SHU Tahun Berjalan (Belum Ditutup, dihitung otomatis) SHU Tahun Berjalan = Σ kontribusi PENDAPATAN − Σ kontribusi BEBAN (kumulatif s.d. tanggal neraca) | E50: Baris SHU berjalan dihitung, bukan akun. Total seksi = Σ akun rinci; akun induk menampilkan roll-up anak (LAP-10), akun kontra mengurangi seksinya (LAP-11). | F50: Seimbang bila |Aset − (Kewajiban + Ekuitas)| < 0,01. Setelah Tutup Buku (LAP-15) entri PENUTUP ikut dihitung, sehingga PENDAPATAN/BEBAN tahun lalu bernilai nol dan hasilnya berpindah ke akun ekuitas tujuan. | G50: Decimal | H50: reports/regulatory-service.ts getNeraca
A51: LAP-03 | B51: Laporan | C51: Alokasi SHU | D51: Pool_k = SHU × %_k untuk k ∈ {Jasa Simpanan, Jasa Pinjaman, Cadangan, Lainnya} | E51: % dari Konfigurasi SHU | F51: Dibagi ke anggota hanya bila SHU > 0 | G51: number (float) | H51: reports/regulatory-service.ts getShuDistribution | I51: AD/ART | J51: L
A52: LAP-04 | B52: Laporan | C52: Jasa Simpanan per anggota | D52: RataSaldo_i = (saldo awal + saldo akhir periode) ÷ 2 JS_i = RataSaldo_i ÷ Σ RataSaldo × Pool JS | E52: Anggota aktif | G52: number (float) | H52: reports/regulatory-service.ts | J52: L
A53: LAP-05 | B53: Laporan | C53: Jasa Pinjaman per anggota | D53: JP_i = Bunga dibayar_i ÷ Σ Bunga dibayar × Pool JP | E53: Bunga dibayar dari pembayaran pinjaman dalam periode (PIN-09) | G53: number (float) | H53: reports/regulatory-service.ts | J53: L
A54: LAP-06 | B54: Laporan | C54: Rincian SHU simpanan | D54: SHU Sukarela = RataSukarela ÷ RataSaldo × JS_i SHU Pokok+Wajib = JS_i − SHU Sukarela Total SHU = JS_i + JP_i | E54: Sisa pembulatan masuk Pokok+Wajib | G54: number (float) | H54: reports/regulatory-service.ts | J54: L
A55: LAP-07 | B55: Laporan | C55: Perubahan Ekuitas | D55: Saldo Akhir_k = Saldo Awal_k + Penambahan_k − Pengurangan_k per kelas ekuitas | E55: Urutan kolom sesuai lampiran Permenkop UKM 2/2024. Saldo awal/akhir kumulatif; mutasi per periode. | F55: Mutasi periode mengecualikan entri PENUTUP, supaya SHU tahun berjalan tampil sebagai penambahan ekuitas, bukan sebagai pemindahan hasil tutup buku. | G55: Decimal | H55: reports/capital-service.ts getPerubahanEkuitas | I55: Permenkop UKM 2/2024
A56: LAP-08 | B56: Laporan | C56: Konsolidasi KSU | D56: Konsolidasi = Σ per unit + bucket 'tidak teralokasi' (JournalEntry.unitId = null) | G56: Decimal | H56: ksu/service.ts; CLAUDE.md aturan 2b
A57: LAP-09 | B57: Laporan | C57: Batas tanggal periode | D57: Dari = awal hari bisnis; Sampai = akhir hari bisnis (23:59:59.999 WIB) | E57: Menggantikan endOfDay waktu server (perbaikan D7) | G57: tanggal | H57: lib/operating-calendar.ts; reports/routes.ts
A58: LAP-10 | B58: Laporan | C58: Roll-up akun induk | D58: Σdebit_induk = Σdebit_akun + Σdebit semua keturunan Σkredit_induk = Σkredit_akun + Σkredit semua keturunan Nilai induk = nilai sisi normal induk dari Σ sisi yang sudah dijumlah | E58: Hirarki dari Account.parentId, bukan rentang kode. Induk hanya untuk tampilan; total seksi menjumlah akun rinci saja. | F58: Menjumlah sisi debit/kredit mentah (bukan saldo bertanda) agar anak kontra tetap benar. Siklus induk dihentikan, bukan berulang tanpa akhir. | G58: Decimal | H58: lib/account-tree.ts rollUpSums, orderDepthFirst | J58: P
A59: LAP-11 | B59: Laporan | C59: Akun kontra | D59: Kontra ⇔ sisi normal ≠ sisi alami kategori (ASET, BEBAN = DEBIT; lainnya = KREDIT) Kontribusi ke seksi = −NilaiSisiNormal bila kontra, else +NilaiSisiNormal NilaiSisiNormal = Debit − Kredit (DEBIT) atau Kredit − Debit (KREDIT) | E59: Contoh: Penyisihan Kerugian Piutang, Prive, Retur Penjualan. Tanpa flag tersimpan, supaya tidak bisa menyimpang dari data. | F59: Neraca Saldo (LAP-12) tidak melakukan netting kontra: tiap akun ditampilkan pada sisi sebenarnya. | G59: Decimal | H59: lib/account-tree.ts isContraAccount, reportContribution | J59: P
A60: LAP-12 | B60: Laporan | C60: Neraca Saldo | D60: SaldoAwal = NilaiSisiNormal(Σ semua entri sebelum periode) Mutasi D/K = Σ debit / Σ kredit dalam periode SaldoAkhir = SaldoAwal + NilaiSisiNormal(mutasi) | E60: Akun induk = roll-up anak (LAP-10). Entri PENUTUP ikut dihitung. Scope unit: semua / satu unit / bucket tidak teralokasi (LAP-08). | F60: Seimbang ⇔ ΣMutasi Debit = ΣMutasi Kredit dan Σ SaldoAkhir akun DEBIT = Σ SaldoAkhir akun KREDIT, hanya atas akun rinci. Buku Besar ringkasan = Neraca Saldo tanpa akun yang seluruhnya nol. | G60: Decimal | H60: reports/ledger-service.ts getNeracaSaldo, getBukuBesar
A61: LAP-13 | B61: Laporan | C61: Buku Besar — saldo berjalan | D61: Saldo_i = SaldoAwal + Σ(j≤i) tanda(debit_j, kredit_j) tanda = Debit − Kredit (akun DEBIT) atau Kredit − Debit (akun KREDIT) SaldoAkhir = SaldoAwal + Σ tanda dalam periode | E61: Urutan baris: tanggal entri, nomor entri (LAN-07), id. Antar halaman saldo tetap menyambung karena mutasi baris sebelum halaman dilipat ke saldo awal halaman. | F61: Akun induk ditolak (tidak punya mutasi sendiri). | G61: Decimal | H61: reports/ledger-service.ts getBukuBesarAccount
A62: LAP-14 | B62: Laporan | C62: Periode pembanding (Neraca, Hasil Usaha, Neraca Saldo) | D62: PREVIOUS_YEAR: [dari, sampai] digeser 12 bulan PREVIOUS_PERIOD, bulan kalender penuh: digeser n bulan, n = jumlah bulan PREVIOUS_PERIOD lainnya: L = sampai − dari + 1 hari; pembanding = [dari − L, dari − 1] Neraca (tanggal): digeser 1 bulan (PREVIOUS_PERIOD) atau 12 bulan (PREVIOUS_YEAR) | E62: Tanggal yang tidak ada di bulan tujuan dijepit ke hari terakhir bulan (31 Mar → 28 Feb); akhir bulan tetap akhir bulan. | F62: Aritmetika tanggal pada string YYYY-MM-DD dengan UTC, sehingga zona waktu server tidak menggeser batas satu hari. | G62: tanggal | H62: lib/comparison.ts comparisonRange, comparisonAsOf
A63: LAP-15 | B63: Laporan | C63: Tutup Buku (penutupan tahun) | D63: Saldo_a = Σdebit − Σkredit akun PENDAPATAN/BEBAN a, per (unit, akun), entri non-PENUTUP tahun itu Tiap akun: Saldo_a > 0 → Kredit akun sebesar Saldo_a; Saldo_a < 0 → Debit akun sebesar |Saldo_a| SHU = −Σ Saldo_a; SHU > 0 → Kredit akun tujuan; SHU < 0 → Debit akun tujuan | E63: Satu entri PENUTUP per unit ditambah satu untuk bucket tidak teralokasi, sehingga jumlah per unit tetap kembali ke konsolidasi. Akun tujuan bawaan 3-3100 SHU Tahun Lalu; harus EKUITAS rinci aktif. | F63: Hanya tahun yang sudah berakhir (≥ 2000 dan < tahun bisnis berjalan). Ditolak bila masih ada entri UNPOSTED_MISSING_MAPPING di tahun itu atau tahun sudah ditutup. Jurnal manual ke tahun tertutup ditolak sampai dibuka kembali. Entri bertanggal 31 Des. | G63: Decimal | H63: modules/journal/year-close.ts planYearClose, closeYear, assertFiscalYearOpen | J63: O
A64: LAP-16 | B64: Laporan | C64: Buka kembali tahun buku | D64: Untuk tiap entri PENUTUP tahun itu: entri cermin dengan Debit ↔ Kredit ditukar (reversalOfId menunjuk entri asal) | E64: Tidak ada yang dihapus; jejak audit memuat penutupan dan pembukaan kembali. | F64: Tidak bisa dibuka bila ada tahun lebih baru yang masih tertutup (saldo awalnya bertumpu pada tahun ini). Tidak bisa dibuka dua kali. | G64: Decimal | H64: modules/journal/year-close.ts reopenYear | J64: O
A65: LAN-01 | B65: Anggota | C65: Nomor anggota | D65: KOP-{SLUG}-{YYYYMM}-{urut 4 digit} | E65: Urutan = jumlah anggota dengan prefiks sama + 1 | F65: Tidak aman terhadap pembuatan bersamaan (Temuan T6) | G65: teks | H65: lib/id-generator.ts generateMemberId
A66: LAN-02 | B66: Anggota | C66: Nomor rekening | D66: ACC-{10 digit acak}, diulang sampai unik global | G66: teks | H66: lib/id-generator.ts generateAccountNumber
A67: LAN-03 | B67: Sistem | C67: Tanggal bisnis | D67: Tanggal bisnis = tanggal UTC + 7 jam (Asia/Jakarta, tanpa DST) | G67: tanggal | H67: lib/operating-calendar.ts businessDate
A68: LAN-04 | B68: Sistem | C68: Penghapusan jejak audit | D68: Hapus baris dengan createdAt < hari ini − 90 hari | E68: Dijalankan harian lintas tenant | G68: tanggal | H68: audit-log/service.ts purgeStaleAuditLogs
A69: LAN-05 | B69: Sistem | C69: Validasi nominal uang | D69: Nominal = string/angka ≤ 13 digit bulat, ≤ 2 desimal → Decimal(15,2) | E69: Angka float seperti 0.30000000000000004 ditolak | G69: Decimal | H69: lib/money.ts moneySchema | I69: CLAUDE.md aturan 2
A70: LAN-06 | B70: Sistem | C70: Keseimbangan jurnal | D70: Σ Debit = Σ Kredit (2 desimal), else ditolak | E70: Setiap entri jurnal otomatis | G70: Decimal | H70: lib/journal.ts
A71: LAN-07 | B71: Sistem | C71: Nomor entri jurnal | D71: entryNo = Tenant.journalSeq + 1 (kenaikan atomik per tenant) | E71: Nomor urut per tenant untuk setiap entri jurnal, otomatis maupun manual. | F71: Kenaikan atomik dalam transaksi yang sama dengan entri, sehingga posting bersamaan tidak berbagi nomor (berbeda dengan LAN-01). | G71: Integer | H71: lib/journal.ts nextEntryNo

Sheet Simulasi
A1: Simulasi Rumus
A2: Sel kuning berteks biru = input; ubah nilainya dan hasil (hitam) dihitung ulang. Teks hijau = rujukan ke sheet Parameter.
A5: A. Pinjaman Anuitas — KONVENSIONAL + BUNGA, angsuran bulanan (lib/loan-calc.ts)
A6: Pokok pinjaman (P) | B6: 10000000 | C6: Input
A7: Bunga per tahun | B7: 0.18 | C7: Input
A8: Tenor (bulan, n) | B8: 12 | C8: Input
A9: Batas bunga regulasi | B9: =Parameter!$C$5 | C9: Dari Parameter!C5
A10: Lolos batas bunga? | B10: =IF(B7<=B9,"YA","DITOLAK — melebihi batas") | C10: validateRegulatoryRate
A11: Bunga per bulan (r) | B11: =B7/12 | C11: r = bunga tahunan ÷ 12
A12: Angsuran per bulan | B12: =IF(B11=0,ROUND(B6/B8,2),ROUND(B6*B11/(1-(1+B11)^(-B8)),2)) | C12: P × r ÷ (1 − (1 + r)^−n); jika r = 0 → P ÷ n
A13: Total dibayar | B13: =IF(B11=0,B6,ROUND(B6*B11/(1-(1+B11)^(-B8))*B8,2)) | C13: Angsuran (belum dibulatkan) × n
A14: Total bunga | B14: =ROUND(B13-B6,2) | C14: Total − P
A16: B. Pinjaman Flat / Margin — SYARIAH atau rateType MARGIN (lib/loan-calc.ts)
A17: Pokok / harga pokok (P) | B17: 10000000 | C17: Input
A18: Margin per tahun | B18: 0.18 | C18: Input
A19: Tenor (bulan, n) | B19: 12 | C19: Input
A20: Total margin | B20: =ROUND(B17*B18*B19/12,2) | C20: P × margin × n ÷ 12
A21: Total dibayar | B21: =ROUND(B17+B17*B18*B19/12,2) | C21: P + margin
A22: Angsuran per bulan | B22: =ROUND((B17+B17*B18*B19/12)/B19,2) | C22: Total ÷ n
A24: C. Pinjaman Harian (flat) + Jadwal Cicilan Pasar — rateType HARIAN, frekuensi DAILY
A25: Pokok pinjaman (P) | B25: 5000000 | C25: Input
A26: Bunga per tahun | B26: 0.24 | C26: Input
A27: Frekuensi (DAILY / WEEKLY / MONTHLY) | B27: DAILY | C27: Input: DAILY, WEEKLY atau MONTHLY
A28: Jumlah cicilan | B28: 100 | C28: Input. MONTHLY: sama dengan tenor bulan
A29: Hari per tahun (konvensi) | B29: =Parameter!$C$11 | C29: Dari Parameter!C11
A30: Unit pembulatan | B30: =Parameter!$C$12 | C30: Dari Parameter!C12
A31: Hari tenor (termDays) | B31: =IF(B27="DAILY",B28,IF(B27="WEEKLY",B28*7,B28*30)) | C31: DAILY = jumlah cicilan; WEEKLY = × 7. MONTHLY memakai hari kalender riil sampai jatuh tempo (≈ × 30 di sini)
A32: Tenor bulan untuk kalkulasi | B32: =IF(B27="MONTHLY",B28,MAX(1,ROUNDUP(B31/30,0))) | C32: MAX(1, ROUNDUP(hari ÷ 30)) untuk DAILY/WEEKLY — lihat Temuan T4
A33: Total bunga | B33: =ROUND(B25*B26/B29*B31,2) | C33: P × bunga ÷ 360 × hari tenor
A34: Total dibayar | B34: =ROUND(B25+B25*B26/B29*B31,2) | C34: P + bunga
A35: Bagian rata (Total ÷ cicilan) | B35: =B34/B28
A36: Nominal cicilan ke-1 s/d n−1 | B36: =IF(B27="MONTHLY",ROUND(B35,2),ROUNDUP(B35/B30,0)*B30) | C36: DAILY/WEEKLY: dibulatkan KE ATAS ke kelipatan Rp500; MONTHLY: 2 desimal
A37: Nominal cicilan terakhir | B37: =ROUND(B34-(B28-1)*B36,2) | C37: Sisa, sehingga Σ cicilan = Total persis
A38: Porsi pokok cicilan ke-1 | B38: =ROUND(B36*B25/B34,2) | C38: Cicilan × P ÷ Total (cicilan terakhir menyerap sisa)
A39: Porsi bunga cicilan ke-1 | B39: =ROUND(B36-B38,2) | C39: Cicilan − porsi pokok
A41: D. Bunga Simpanan (lib/saving-calc.ts, savings/daily-interest.ts)
A42: Saldo simpanan | B42: 10000000 | C42: Input
A43: Bunga per tahun | B43: 0.06 | C43: Input
A44: Hari sejak lastInterestAt | B44: 3 | C44: Input. Run pertama = 1 hari
A45: Batas bunga simpanan | B45: =Parameter!$C$6 | C45: Dari Parameter!C6
A46: Hari per tahun | B46: =Parameter!$C$11 | C46: Dari Parameter!C11
A47: Lolos batas bunga? | B47: =IF(B43<=B45,"YA","DITOLAK — melebihi batas")
A48: Bunga harian | B48: =ROUND(B42*B43/B46,2) | C48: Saldo × bunga ÷ 360, dibulatkan per hari
A49: Bunga dikreditkan run ini | B49: =ROUND(B42*B43/B46,2)*B44 | C49: Bunga harian (sudah dibulatkan) × hari terlewat
A50: Bunga periode MONTHLY | B50: =ROUND(B42*B43/12,2) | C50: Saldo × bunga ÷ 12
A51: Bunga periode YEARLY | B51: =ROUND(B42*B43,2) | C51: Saldo × bunga
A53: E. Rekening Koran (savings/service.ts getSavingStatement)
A54: Saldo saat ini (Saving.balance) | B54: 12000000 | C54: Input
A55: Mutasi bersih SETELAH akhir periode | B55: 500000 | C55: Input: setoran + bunga − penarikan setelah periode
A56: Setoran dalam periode (Kredit) | B56: 3000000 | C56: Input
A57: Bunga dalam periode (Kredit) | B57: 50000 | C57: Input
A58: Penarikan dalam periode (Debit) | B58: 1000000 | C58: Input
A59: Saldo Akhir | B59: =B54-B55 | C59: Saldo sekarang − mutasi setelah periode
A60: Saldo Awal | B60: =B59-(B56+B57-B58) | C60: Saldo Akhir − (Kredit − Debit) dalam periode
A62: F. BMPP — Batas Maksimum Pemberian Pinjaman (loans/service.ts computeBmpp)
A63: Modal Sendiri (unit pemberi pinjaman bila KSU) | B63: 2000000000 | C63: Input
A64: Pihak terkait? (YA / TIDAK) | B64: TIDAK | C64: Input: YA untuk pengurus/pengawas
A65: Pokok pinjaman aktif anggota | B65: 150000000 | C65: Input
A66: Pokok pinjaman baru | B66: 200000000 | C66: Input
A67: Persentase BMPP | B67: =IF(B64="YA",Parameter!$C$7,Parameter!$C$8) | C67: 10% pihak terkait, 15% lainnya
A68: Batas BMPP | B68: =B63*B67 | C68: Modal Sendiri × persentase
A69: Sisa ruang (headroom) | B69: =MAX(0,B68-B65) | C69: MAX(0, batas − pinjaman aktif)
A70: Pinjaman aktif + baru | B70: =B65+B66
A71: Hasil | B71: =IF(B64="YA",IF(B70>B68,"DITOLAK (Pasal 44)","OK"),IF(AND(B63>0,B70>B68),"PERINGATAN — perlu konfirmasi (Pasal 45)","OK")) | C71: Pihak terkait: blokir keras. Lainnya: peringatan, hanya bila Modal Sendiri > 0
A73: G. Kredit Anggota Toko (konsumen/credit.service.ts)
A74: Total saldo simpanan aktif (semua jenis) | B74: 4000000 | C74: Input
A75: Punya simpanan aktif? (YA / TIDAK) | B75: YA | C75: Input
A76: Total belanja kredit (MEMBER_CREDIT) | B76: 1500000 | C76: Input
A77: Total pelunasan | B77: 500000 | C77: Input
A78: Rasio limit | B78: =Parameter!$C$10 | C78: Dari Parameter!C10
A79: Limit kredit | B79: =B74*B78 | C79: Total simpanan × 50%, dihitung ulang setiap dibaca
A80: Piutang berjalan | B80: =B76-B77 | C80: Belanja kredit − pelunasan
A81: Sisa kredit tersedia | B81: =B79-B80 | C81: Limit − piutang
A82: Berhak kredit? | B82: =IF(AND(B75="YA",B79>0),"YA","TIDAK")
A84: H. Kolektibilitas (lib/kol.ts)
A85: Hari tunggakan | B85: 95 | C85: Input: hari ini − jatuh tempo cicilan belum lunas tertua
A86: KOL | B86: =IF(B85<=Parameter!$C$14,"LANCAR",IF(B85<=Parameter!$C$15,"DALAM PERHATIAN",IF(B85<=Parameter!$C$16,"KURANG LANCAR",IF(B85<=Parameter!$C$17,"DIRAGUKAN","MACET")))) | C86: ≤30 / ≤90 / ≤120 / ≤180 / >180 hari
A88: I. Kualitas Pinjaman (dashboard/service.ts getLoanQualityDashboard)
A89: Outstanding LANCAR | B89: 800000000 | C89: Input
A90: Outstanding DALAM PERHATIAN | B90: 60000000 | C90: Input
A91: Outstanding KURANG LANCAR | B91: 20000000 | C91: Input
A92: Outstanding DIRAGUKAN | B92: 10000000 | C92: Input
A93: Outstanding MACET | B93: 10000000 | C93: Input
A94: Saldo simpanan non-ekuitas (Sukarela) | B94: 1200000000 | C94: Input
A95: Total outstanding | B95: =SUM(B89,B90,B91,B92,B93) | C95: Σ remainingAmount pinjaman ACTIVE
A96: Rasio NPL | B96: =IF(B95=0,"-",(B91+B92+B93)/B95) | C96: (KL + D + M) ÷ total outstanding
A97: LDR | B97: =IF(B94=0,"-",B95/B94) | C97: Total outstanding ÷ simpanan non-ekuitas
A99: J. Modal Sendiri & Ambang Audit (reports/capital-service.ts, config/audit-threshold.ts)
A100: Saldo Simpanan Pokok | B100: 300000000 | C100: Termasuk
A101: Saldo Simpanan Wajib | B101: 900000000 | C101: Termasuk
A102: Saldo Modal Tetap | B102: 0 | C102: Termasuk
A103: Saldo Cadangan Umum | B103: 400000000 | C103: Termasuk
A104: Saldo Cadangan Risiko | B104: 100000000 | C104: Termasuk
A105: Saldo Hibah | B105: 50000000 | C105: Termasuk
A106: Saldo Modal Penyertaan | B106: 250000000 | C106: TIDAK termasuk
A107: SHU belum dibagi | B107: 120000000 | C107: TIDAK termasuk
A108: Penyesuaian saldo awal (terbaru) | B108: 0 | C108: ModalSendiriAdjustment
A109: Total Aset | B109: 6000000000 | C109: Input
A110: Modal Sendiri per 31 Des tahun lalu | B110: 1600000000 | C110: Input
A111: Punya unit KSP aktif? (YA / TIDAK) | B111: YA | C111: Input
...

Sheet Parameter
A1: Parameter & Konstanta
A2: Nilai tetap di kode. Teks biru = input (ubah untuk simulasi). Sheet Simulasi merujuk sel-sel ini.
A4: Kode | B4: Parameter | C4: Nilai | D4: Satuan | E4: Dasar / Alasan | F4: Sumber Kode
A5: P01 | B5: Batas bunga pinjaman per tahun | C5: 0.24 | D5: % / tahun | E5: Permenkop UKM 8/2023 Pasal 27 | F5: lib/regulatory-config.ts REGULATORY_CAPS
A6: P02 | B6: Batas bunga simpanan per tahun | C6: 0.09 | D6: % / tahun | E6: Permenkop UKM 8/2023 Pasal 26 | F6: lib/regulatory-config.ts REGULATORY_CAPS
A7: P03 | B7: BMPP pihak terkait (pengurus/pengawas) | C7: 0.1 | D7: % Modal Sendiri | E7: Permenkop UKM 8/2023 Pasal 44 — blokir keras | F7: lib/regulatory-config.ts; loans/service.ts computeBmpp
A8: P04 | B8: BMPP anggota lain (tidak terkait) | C8: 0.15 | D8: % Modal Sendiri | E8: Pasal 45 — hanya peringatan, bisa dikonfirmasi | F8: loans/service.ts (acknowledgeBmpp)
A9: P05 | B9: Ambang wajib audit KAP | C9: 5000000000 | D9: Rupiah | E9: Permenkop UKM 2/2024 Pasal 12 (Rp5 miliar); diukur dari Modal Sendiri | F9: lib/regulatory-config.ts MODAL_DISETOR_AUDIT_THRESHOLD_RP
A10: P06 | B10: Limit Kredit Anggota dari total simpanan | C10: 0.5 | D10: rasio | E10: Keputusan produk (Kredit Anggota) | F10: konsumen/credit.service.ts CREDIT_LIMIT_RATIO
A11: P07 | B11: Konvensi hari per tahun | C11: 360 | D11: hari | E11: Konvensi 12 × 30 hari (bunga harian & simpanan) | F11: lib/saving-calc.ts; lib/loan-calc.ts
A12: P08 | B12: Pembulatan cicilan harian/mingguan | C12: 500 | D12: Rupiah | E12: Keputusan pasar D8 — dibulatkan ke atas | F12: lib/installment-schedule.ts ROUNDING_UNIT
A13: P09 | B13: Ambang konsentrasi simpanan pokok+wajib | C13: 0.2 | D13: % Modal Sendiri | E13: Indikator dashboard (bukan aturan) | F13: dashboard/service.ts MEMBER_CAPITAL_CONCENTRATION_PCT
A14: P10 | B14: KOL Lancar: tunggakan maks. | C14: 30 | D14: hari | E14: Keputusan pasar D2 (tidak diubah) | F14: lib/kol.ts getKOLCategory
A15: P11 | B15: KOL Dalam Perhatian: tunggakan maks. | C15: 90 | D15: hari | F15: lib/kol.ts
A16: P12 | B16: KOL Kurang Lancar: tunggakan maks. | C16: 120 | D16: hari | F16: lib/kol.ts
A17: P13 | B17: KOL Diragukan: tunggakan maks. (> = Macet) | C17: 180 | D17: hari | F17: lib/kol.ts
A18: P14 | B18: Retensi jejak audit | C18: 90 | D18: hari | E18: Dihapus harian oleh scheduler | F18: audit-log/service.ts RETENTION_DAYS
A19: P15 | B19: Periode maks. Rekening Koran | C19: 366 | D19: hari | F19: savings/service.ts statement
A20: P16 | B20: Batas pendaftaran mandiri per IP | C20: 5 | D20: per jam | E20: Default, dapat dikonfigurasi | F20: members/public-registration.routes.ts
A21: P17 | B21: Zona waktu tanggal bisnis | C21: 7 | D21: jam (UTC+7) | E21: Asia/Jakarta, tanpa DST | F21: lib/operating-calendar.ts businessDate
A22: P18 | B22: Akun tujuan penutupan default | C22: 3-3100 | D22: kode akun | E22: Akun SHU Tahun Lalu; dapat diganti ke akun EKUITAS rinci aktif lain | F22: modules/journal/year-close.ts resolveTarget
A24: Batas Klasifikasi KSP — Permenkop UKM 8/2023 Pasal 49 (lib/regulatory-config.ts KSP_CLASS_BOUNDS). Melewati salah satu batas = naik kelas.
A25: Kelas | B25: Jumlah anggota maks. | C25: Modal Sendiri maks. | E25: Aset maks.
A26: KSP I | B26: 5000 | C26: 2500000000 | E26: 15000000000
A27: KSP II | B27: 10000 | C27: 15000000000 | E27: 100000000000
A28: KSP III | B28: 30000 | C28: 50000000000 | E28: 500000000000
A29: Di atas KSP III = KSP IV.

Sheet Jurnal Otomatis
A1: Jurnal Otomatis per Transaksi
A2: Akun default dari COA standar (lib/coaTemplate.ts); dapat dipetakan ulang di Konfigurasi → Pemetaan Akun.
A4: Transaksi | B4: Jenis Pemetaan | C4: Debit | D4: Kredit | E4: Jumlah | F4: Catatan
A5: Setoran simpanan | B5: DEPOSIT | C5: Kas | D5: Simpanan (Pokok/Wajib/Sukarela) | E5: Setoran | F5: Per produk simpanan
A6: Penarikan simpanan | B6: WITHDRAWAL | C6: Simpanan | D6: Kas | E6: Penarikan
A7: Bunga simpanan harian | B7: SAVING_INTEREST | C7: Beban Bunga/Bagi Hasil Simpanan | D7: Simpanan | E7: SIM-02 | F7: Tidak dipetakan otomatis — jurnal UNPOSTED sampai dipetakan (Temuan T7)
A8: Pencairan pinjaman | B8: DISBURSEMENT | C8: Piutang Pinjaman Anggota | D8: Kas | E8: Pokok | F8: Default per produk pinjaman
A9: Angsuran — pokok | B9: PAYMENT_PRINCIPAL | C9: Kas | D9: Piutang Pinjaman Anggota | E9: PIN-08
A10: Angsuran — bunga | B10: PAYMENT_INTEREST | C10: Kas | D10: Pendapatan Bunga/Margin Pinjaman | E10: PIN-08
A11: Angsuran — denda | B11: PAYMENT_PENALTY | C11: Kas | D11: Pendapatan Lain-lain | E11: Input manual
A12: Penjualan tunai | B12: SALE_REVENUE | C12: Kas | D12: Penjualan Barang Dagang | E12: TOK-01 Total | F12: Semua-atau-tidak-sama-sekali dengan HPP
A13: Penjualan kredit anggota | B13: SALE_RECEIVABLE | C13: Piutang Anggota (Toko) | D13: Penjualan Barang Dagang | E13: TOK-01 Total
A14: HPP penjualan | B14: SALE_COGS | C14: Harga Pokok Penjualan | D14: Persediaan Barang Dagang | E14: TOK-01 HPP
A15: Pelunasan kredit anggota | B15: MEMBER_CREDIT_REPAYMENT | C15: Kas | D15: Piutang Anggota (Toko) | E15: Pelunasan | F15: Unit: tidak teralokasi
A16: Restock toko | B16: STOCK_PURCHASE | C16: Persediaan Barang Dagang | D16: Kas (atau Utang Usaha) | E16: TOK-02
A17: Transaksi oleh kolektor | B17: COLLECTOR_CASH | C17: Kas di Kolektor (menggantikan Kas) | D17: (sesuai transaksi) | E17: Setoran | F17: Kas diganti Kas di Kolektor sampai diverifikasi
A18: Verifikasi batch kolektor | B18: COLLECTOR_CASH | C18: Kas = diterima; Piutang Kolektor = kekurangan | D18: Kas di Kolektor = diharapkan; Selisih Kas = kelebihan | E18: PAS-06 | F18: Entri majemuk
A19: Tagihan sewa (akrual) | B19: CHARGE_ACCRUAL_SEWA | C19: Piutang Sewa & Retribusi | D19: Pendapatan Sewa Kios | E19: PAS-01
A20: Tagihan retribusi (akrual) | B20: CHARGE_ACCRUAL_RETRIBUSI | C20: Piutang Sewa & Retribusi | D20: Pendapatan Retribusi | E20: PAS-02 | F20: Keputusan D5: pendapatan
A21: Pembayaran tagihan pasar | B21: CHARGE_PAYMENT | C21: Kas / Kas di Kolektor | D21: Piutang Sewa & Retribusi | E21: Pembayaran
A22: Beban Umum | B22: MANUAL_EXPENSE (sumber) | C22: Akun BEBAN pilihan | D22: Kas/Bank (setara kas) | E22: Input | F22: Unit opsional; hapus, tidak bisa edit
A23: Penutupan buku (per unit + tidak teralokasi) | B23: CLOSING (entryType PENUTUP) | C23: Akun PENDAPATAN bersaldo kredit; akun tujuan 3-3100 bila rugi | D23: Akun BEBAN bersaldo debit; akun tujuan 3-3100 bila laba | E23: LAP-15 | F23: Bertanggal 31 Des; saldo tiap akun dinolkan
A24: Pembukaan kembali tahun buku | B24: CLOSING (entryType PENUTUP) | C24: Cermin: kredit entri penutup menjadi debit | D24: Cermin: debit entri penutup menjadi kredit | E24: LAP-16 | F24: reversalOfId menunjuk entri asal; tidak ada yang dihapus
A25: Jurnal manual | B25: MANUAL (UMUM atau PENYESUAIAN) | C25: Akun pilihan (Σ Debit) | D25: Akun pilihan (Σ Kredit) | E25: LAN-06 | F25: Ditolak pada tahun buku tertutup; PENYESUAIAN untuk koreksi akhir periode

Sheet Temuan
A1: Temuan dari Review Rumus
A2: Hal yang terlihat saat menyusun daftar ini. Belum ditriase Engineer/QA.
A4: ID | B4: Temuan | C4: Detail | D4: Lokasi | E4: Rumus
A5: T1 | B5: Bunga simpanan dihitung dengan float | C5: calculateSavingInterest memakai number, melanggar CLAUDE.md aturan 2. Jalur akrual harian scheduler sudah Decimal, jadi dua jalur bisa berbeda di sen terakhir. | D5: lib/saving-calc.ts | E5: SIM-01
A6: T2 | B6: Kalkulasi pinjaman dengan float | C6: calculateLoan menerima principal.toNumber() dan menghitung dalam number sebelum jadwal Decimal dibangun. Total & bunga bisa meleset sen pada nilai besar. | D6: lib/loan-calc.ts; loans/service.ts | E6: PIN-01..03
A7: T3 | B7: Pembagian SHU dengan float | C7: getShuDistribution memakai Number() dan round2 untuk semua pool dan porsi anggota. Σ porsi anggota bisa tidak sama persis dengan pool. | D7: reports/regulatory-service.ts | E7: LAP-03..06
A8: T4 | B8: Margin flat untuk DAILY/WEEKLY memakai bulan dibulatkan ke atas | C8: TenorBulan = ROUNDUP(hari ÷ 30), jadi pinjaman flat 100 hari dihitung 4 bulan (bukan 3,33). Margin naik sekitar 20%. HARIAN tidak terpengaruh (memakai hari). | D8: loans/service.ts createLoan | E8: PIN-02, PIN-04
A9: T5 | B9: Ambang audit memakai Modal Sendiri, nama konstanta Modal Disetor | C9: Pasal 12 menyebut modal; kode memakai Modal Sendiri buku besar. Konstanta tetap bernama MODAL_DISETOR_AUDIT_THRESHOLD_RP; perlu konfirmasi PM bahwa basisnya memang Modal Sendiri. | D9: config/audit-threshold.ts | E9: MOD-03
A10: T6 | B10: Nomor anggota rawan bentrok | C10: Urutan dihitung dari COUNT, bukan sequence DB. Dua pendaftaran bersamaan di bulan yang sama bisa mendapat nomor sama. | D10: lib/id-generator.ts | E10: LAN-01
A11: T7 | B11: Bunga simpanan harian tidak punya pemetaan default | C11: Generate COA membuat pemetaan DEPOSIT/WITHDRAWAL per produk simpanan, tetapi tidak SAVING_INTEREST. Scheduler menambah saldo simpanan, namun jurnalnya tersimpan UNPOSTED_MISSING_MAPPING sampai admin memetakan manual — Neraca tidak mencerminkan beban bunga. | D11: modules/config/service.ts generateStandardCoa; savings/daily-interest.ts | E11: SIM-02
A12: T8 | B12: Pokok bersaldo nol memenuhi syarat pinjaman | C12: hasPokokSaving hanya memeriksa isActive. Terkait QA D1–D3 dan rencana Setoran Awal yang belum diimplementasikan. | D12: savings/service.ts | E12: PIN-16
A13: T9 | B13: PAR bergantung pada job KOL harian | C13: Laporan Kualitas Portofolio membaca Loan.daysOverdue yang terakhir ditulis job harian (recalculateAllKOL). Bila job gagal atau belum jalan, angka PAR basi tanpa tanda apa pun di laporan. | D13: reports/portfolio-service.ts; lib/kol.ts | E13: KUA-05
A14: T10 | B14: Efisiensi penagihan memakai 'terbayar sampai sekarang' | C14: principalPaid + interestPaid bersifat kumulatif, bukan terbayar sampai akhir periode. Efisiensi bulan lampau naik seiring waktu dan tidak bisa direproduksi persis di kemudian hari. | D14: reports/portfolio-service.ts getCollectionEfficiency | E14: KUA-08
A15: T11 | B15: Outstanding pinjaman tanpa jadwal memakai porsi pokok flat | C15: Fallback remainingAmount × pokok ÷ total mengandaikan pembayaran terdistribusi proporsional; untuk pinjaman anuitas lama hanya pendekatan. | D15: reports/portfolio-service.ts outstandingSql | E15: KUA-07
